radicalpy/__init__.py
radicalpy/classical.py
radicalpy/data.py
radicalpy/estimations.py
radicalpy/experiments.py
radicalpy/kinetics.py
radicalpy/plot.py
radicalpy/py.typed
radicalpy/relaxation.py
radicalpy/shared.py
radicalpy/simulation.py
radicalpy/tensornetwork.py
radicalpy/utils.py
radicalpy/data_files/constants.json
radicalpy/data_files/spin_data.json
radicalpy/data_files/molecules/2_6_aqds.json
radicalpy/data_files/molecules/adenine_cation.json
radicalpy/data_files/molecules/fad.json
radicalpy/data_files/molecules/flavin_anion.json
radicalpy/data_files/molecules/flavin_neutral.json
radicalpy/data_files/molecules/tryptophan_cation.json
radicalpy/data_files/molecules/tyrosine_neutral.json
radicalpy-1.0.9.dist-info/licenses/LICENSE
radicalpy-1.0.9.dist-info/METADATA
radicalpy-1.0.9.dist-info/WHEEL
radicalpy-1.0.9.dist-info/top_level.txt
radicalpy-1.0.9.dist-info/RECORD
