Metadata-Version: 2.4
Name: radicalpy
Version: 1.0.9
Summary: RadicalPy: a toolbox for radical pair spin dynamics
Author-email: "Lewis M. Antill" <lewismantill@gmail.com>, Emil Vatai <emil.vatai@gmail.com>
Maintainer-email: Emil Vatai <emil.vatai@gmail.com>, "Lewis M. Antill" <lewismantill@gmail.com>
License: MIT
Project-URL: Homepage, https://github.com/Spin-Chemistry-Labs/radicalpy
Project-URL: Documentation, https://radicalpy.readthedocs.io/en/latest/
Project-URL: Source, https://github.com/Spin-Chemistry-Labs/radicalpy
Keywords: simulation,spin-dynamics,radical pairs
License-File: LICENSE
Requires-Dist: importlib_resources
Requires-Dist: matplotlib
Requires-Dist: numpy
Requires-Dist: pint
Requires-Dist: scikit-learn
Requires-Dist: scipy
Requires-Dist: seaborn
Requires-Dist: sympy
Requires-Dist: tqdm
Requires-Dist: graphviz
Requires-Dist: dot2tex
Requires-Dist: rdkit
Requires-Dist: MDAnalysis
Dynamic: license-file
